SitanfuCs183bYcChuangyeKeWenzibanChuangjian/README.md
SitanfuCs183bYcChuangyeKeWenzibanChuangjian/__init__.py
SitanfuCs183bYcChuangyeKeWenzibanChuangjian/__main__.py
SitanfuCs183bYcChuangyeKeWenzibanChuangjian/file.epub
SitanfuCs183bYcChuangyeKeWenzibanChuangjian/index.html
SitanfuCs183bYcChuangyeKeWenzibanChuangjian/css/__init__.py
SitanfuCs183bYcChuangyeKeWenzibanChuangjian/css/annotations.css
SitanfuCs183bYcChuangyeKeWenzibanChuangjian/css/main.css
SitanfuCs183bYcChuangyeKeWenzibanChuangjian/css/normalize.css
SitanfuCs183bYcChuangyeKeWenzibanChuangjian/css/popup.css
SitanfuCs183bYcChuangyeKeWenzibanChuangjian/font/__init__.py
SitanfuCs183bYcChuangyeKeWenzibanChuangjian/font/fontello.eot
SitanfuCs183bYcChuangyeKeWenzibanChuangjian/font/fontello.svg
SitanfuCs183bYcChuangyeKeWenzibanChuangjian/font/fontello.ttf
SitanfuCs183bYcChuangyeKeWenzibanChuangjian/font/fontello.woff
SitanfuCs183bYcChuangyeKeWenzibanChuangjian/img/__init__.py
SitanfuCs183bYcChuangyeKeWenzibanChuangjian/img/annotator-glyph-sprite.png
SitanfuCs183bYcChuangyeKeWenzibanChuangjian/img/annotator-icon-sprite.png
SitanfuCs183bYcChuangyeKeWenzibanChuangjian/img/apple-touch-icon.png
SitanfuCs183bYcChuangyeKeWenzibanChuangjian/img/cancelfullscreen.png
SitanfuCs183bYcChuangyeKeWenzibanChuangjian/img/close.png
SitanfuCs183bYcChuangyeKeWenzibanChuangjian/img/fullscreen.png
SitanfuCs183bYcChuangyeKeWenzibanChuangjian/img/loader.gif
SitanfuCs183bYcChuangyeKeWenzibanChuangjian/img/menu-icon.png
SitanfuCs183bYcChuangyeKeWenzibanChuangjian/img/save.png
SitanfuCs183bYcChuangyeKeWenzibanChuangjian/img/saved.png
SitanfuCs183bYcChuangyeKeWenzibanChuangjian/img/settings-s.png
SitanfuCs183bYcChuangyeKeWenzibanChuangjian/img/settings.png
SitanfuCs183bYcChuangyeKeWenzibanChuangjian/img/star.png
SitanfuCs183bYcChuangyeKeWenzibanChuangjian/js/__init__.py
SitanfuCs183bYcChuangyeKeWenzibanChuangjian/js/epub.js
SitanfuCs183bYcChuangyeKeWenzibanChuangjian/js/epub.min.js
sitanfu_cs183b_yc_chuangye_ke_wenziban_chuangjian-2024.3.2.0.dist-info/METADATA
sitanfu_cs183b_yc_chuangye_ke_wenziban_chuangjian-2024.3.2.0.dist-info/WHEEL
sitanfu_cs183b_yc_chuangye_ke_wenziban_chuangjian-2024.3.2.0.dist-info/entry_points.txt
sitanfu_cs183b_yc_chuangye_ke_wenziban_chuangjian-2024.3.2.0.dist-info/top_level.txt
sitanfu_cs183b_yc_chuangye_ke_wenziban_chuangjian-2024.3.2.0.dist-info/RECORD
